Metadata-Version: 1.1
Name: httpie-ems-auth-p3
Version: 0.2.2
Summary: EmsAuth plugin for HTTPie.
Home-page: https://github.com/emartech/httpie-ems-auth
Author: Andras Barthazi
Author-email: andras@barthazi.hu
License: MIT
Download-URL: https://github.com/emartech/httpie-ems-auth
Platform: UNKNOWN
Classifier: Development Status :: 3 - Alpha
Classifier: Environment :: Console
Classifier: Programming Language :: Python
Classifier: Intended Audience :: Developers
Classifier: Environment :: Plugins
Classifier: License :: OSI Approved :: MIT License
Classifier: Topic :: Internet :: WWW/HTTP
Classifier: Topic :: Utilities
